notion_sync/__init__.py
notion_sync/__main__.py
notion_sync-0.3.2.dist-info/METADATA
notion_sync-0.3.2.dist-info/WHEEL
notion_sync-0.3.2.dist-info/entry_points.txt
notion_sync-0.3.2.dist-info/top_level.txt
notion_sync-0.3.2.dist-info/RECORD
