Metadata-Version: 2.1
Name: notion-sync
Version: 0.3.2
Summary: A tool to sync a notion collection to markdown files
Home-page: https://github.com/adjective-object/notion-sync
Author: Maxwell Huang-Hobbs
Author-email: mhuan13+pypy@gmail.com
License: UNKNOWN
Platform: UNKNOWN
Classifier: Programming Language :: Python :: 3
Classifier: License :: OSI Approved :: MIT License
Classifier: Operating System :: OS Independent
Requires-Python: >=3.7
Requires-Dist: notion
Requires-Dist: urllib3 (>=1.24.2)
